urest
