Metadata-Version: 1.0
Name: urest
Version: 2.3.0
Summary: Tiny Python REST framework
Home-page: https://github.com/fclaerho/urest
Author: florent claerhout
Author-email: code@fclaerhout.fr
License: MIT
Platform: UNKNOWN
